example_python_package_with_rust_backend-1.1.10.dist-info/METADATA
example_python_package_with_rust_backend-1.1.10.dist-info/WHEEL
example_python_package_with_rust_backend-1.1.10.dist-info/license_files/LICENSE.txt
example_python_package_with_rust_backend/__init__.py
example_python_package_with_rust_backend/example_python_package_with_rust_backend.pypy39-pp73-s390x-linux-gnu.so
example_python_package_with_rust_backend-1.1.10.dist-info/RECORD
