Metadata-Version: 2.3
Name: example_python_package_with_rust_backend
Version: 1.1.10
Classifier: Programming Language :: Rust
Classifier: Programming Language :: Python :: Implementation :: CPython
Classifier: Programming Language :: Python :: Implementation :: PyPy
License-File: LICENSE.txt
Requires-Python: >=3.7
